kancylog.py
kancylog-0.0.5.dist-info/METADATA
kancylog-0.0.5.dist-info/WHEEL
kancylog-0.0.5.dist-info/entry_points.txt
kancylog-0.0.5.dist-info/top_level.txt
kancylog-0.0.5.dist-info/RECORD
